{"max_history": 3, "state_featurizer": {"num_features": 16, "input_state_map": {"slot_name_0": 7, "prev_utter_thanks": 12, "prev_action_default_fallback": 10, "prev_action_listen": 8, "intent_greet": 2, "intent_goodbye": 1, "prev_utter_name": 11, "intent_thanks": 5, "prev_action_joke": 15, "prev_utter_greet": 13, "intent_name": 4, "prev_utter_goodbye": 14, "prev_action_restart": 9, "intent_deny": 0, "intent_joke": 3, "entity_name": 6}, "user_feature_len": 7, "slot_feature_len": 1, "py/object": "rasa_core.featurizers.BinarySingleStateFeaturizer"}, "use_intent_probabilities": false, "remove_duplicates": true, "py/object": "rasa_core.featurizers.MaxHistoryTrackerFeaturizer"}